MANIFEST.in
README.rst
config.py
setup.cfg
setup.py
versioneer.py
apt/repo.conf
handi.egg-info/PKG-INFO
handi.egg-info/SOURCES.txt
handi.egg-info/dependency_links.txt
handi.egg-info/entry_points.txt
handi.egg-info/not-zip-safe
handi.egg-info/requires.txt
handi.egg-info/top_level.txt
handy/__init__.py
handy/__main__.py
handy/_version.py
handy/misc.py
handy/pkg.py
handy/setenv.py
handy/version.conf
handy/cli/__init__.py
handy/cli/_constants.py
handy/cli/_file.py
handy/cli/chkinfo.py
handy/cli/cli.py
handy/cli/clipboard.py
handy/cli/config.py
handy/cli/crypt.py
handy/cli/document.py
handy/cli/download.py
handy/cli/filter.py
handy/cli/git.py
handy/cli/hack.py
handy/cli/json.py
handy/cli/math.py
handy/cli/network.py
handy/cli/secure.py
handy/cli/simple.py
handy/cli/text.py
handy/cli/transfer.py
handy/cli/translate.py
handy/cli/utils.py
handy/conv/__init__.py
handy/conv/basics.py
handy/crypto/__init__.py
handy/crypto/encode.py
handy/crypto/encrypt.py
handy/crypto/passcode.py
handy/dict/__init__.py
handy/dict/mixedict.py
handy/dict/puredict.py
handy/document/__init__.py
handy/document/dict2txt.py
handy/document/docx2xml.py
handy/document/list2txt.py
handy/document/pdf2docx.py
handy/document/tmp/[Content_Types].xml
handy/document/tmp/_rels/.rels
handy/document/tmp/docProps/app.xml
handy/document/tmp/docProps/core.xml
handy/document/tmp/word/document.xml
handy/document/tmp/word/fontTable.xml
handy/document/tmp/word/settings.xml
handy/document/tmp/word/styles.xml
handy/document/tmp/word/webSettings.xml
handy/document/tmp/word/_rels/document.xml.rels
handy/document/tmp/word/theme/theme1.xml
handy/file/__init__.py
handy/file/compress.py
handy/file/search.py
handy/hack/__init__.py
handy/hack/crack.py
handy/hack/crawl.py
handy/hack/img2txt.py
handy/hack/mail.py
handy/hack/spoof.py
handy/hack/video2txt.py
handy/jzon/__init__.py
handy/jzon/handler.py
handy/network/__init__.py
handy/network/download.py
handy/network/ftp.py
handy/network/portscan.py
handy/network/upload.py
handy/network/worm.py
handy/rand/__init__.py
handy/rand/gid.py
handy/rand/number.py
handy/rand/passwd.py
handy/tests/__init__.py
handy/tests/test_dict.py
handy/tests/test_encode.py
handy/tests/test_encrypt.py
