Metadata-Version: 2.1
Name: handi
Version: 0.10.4
Summary: legacy commands & utils
Home-page: https://github.com/gustavkkk/handy
Author: gustav0125
Author-email: gustav0125@outlook.com
Maintainer: gustav0125
Maintainer-email: gustav0125@outlook.com
License: MIT
Keywords: utility,basics
Platform: UNKNOWN
Classifier: Development Status :: 4 - Beta
Classifier: Intended Audience :: Developers
Classifier: License :: OSI Approved :: MIT License
Classifier: Natural Language :: English
Classifier: Operating System :: OS Independent
Classifier: Programming Language :: Python :: 2.7
Classifier: Programming Language :: Python :: 3.5
Classifier: Programming Language :: Python :: 3.6
Classifier: Programming Language :: Python :: Implementation :: CPython
Classifier: Programming Language :: Python :: Implementation :: PyPy
Provides-Extra: dev
Provides-Extra: dilate
